draw_isabelle/__init__.py
draw_isabelle/__main__.py
draw_isabelle/parsing.py
draw_isabelle-0.0.2.dist-info/METADATA
draw_isabelle-0.0.2.dist-info/WHEEL
draw_isabelle-0.0.2.dist-info/entry_points.txt
draw_isabelle-0.0.2.dist-info/top_level.txt
draw_isabelle-0.0.2.dist-info/RECORD
