Metadata-Version: 2.1
Name: draw-isabelle
Version: 0.0.2
Summary: Viz Isabelle ⟨l, a, r⟩ graphs
Home-page: https://github.com/sorenmulli/draw-isabelle
Download-URL: https://pypi.org/project/draw-isabelle
Author: Søren Winkel Holm
Author-email: swholm@protonmail.com
License: MIT
Requires-Dist: binarytree (~=6.5.1)
